MANIFEST.in
Makefile
README.rst
__init__.py
debug.py
setup.cfg
setup.py
tests.py
docs/Makefile
docs/conf.py
docs/debug.rst
docs/headers_examples.txt
docs/human_curl.rst
docs/index.rst
docs/make.bat
docs/modules.rst
human_curl/__init__.py
human_curl/async.py
human_curl/auth.py
human_curl/compat.py
human_curl/core.py
human_curl/exceptions.py
human_curl/methods.py
human_curl/utils.py
human_curl.egg-info/PKG-INFO
human_curl.egg-info/SOURCES.txt
human_curl.egg-info/dependency_links.txt
human_curl.egg-info/requires.txt
human_curl.egg-info/top_level.txt